ipuz/__init__.py
ipuz/core.py
ipuz/exceptions.py
ipuz/validators.py
ipuz/puzzlekinds/__init__.py
ipuz/puzzlekinds/acrostic.py
ipuz/puzzlekinds/answer.py
ipuz/puzzlekinds/block.py
ipuz/puzzlekinds/crossword.py
ipuz/puzzlekinds/fill.py
ipuz/puzzlekinds/sudoku.py
ipuz/puzzlekinds/wordsearch.py
ipuz/structures/__init__.py
ipuz/structures/calcspec.py
ipuz/structures/clue.py
ipuz/structures/cluenum.py
ipuz/structures/common.py
ipuz/structures/crosswordvalue.py
ipuz/structures/direction.py
ipuz/structures/enumeration.py
ipuz/structures/groupspec.py
ipuz/structures/labeledcell.py
ipuz/structures/styledcell.py
ipuz/structures/stylespec.py
ipuz/structures/sudokugiven.py
ipuz/structures/sudokuguess.py
ipuz/structures/sudokuvalue.py
ipuz-1.0.dist-info/LICENSE
ipuz-1.0.dist-info/METADATA
ipuz-1.0.dist-info/WHEEL
ipuz-1.0.dist-info/top_level.txt
ipuz-1.0.dist-info/RECORD
