Metadata-Version: 2.1
Name: ipuz
Version: 1.0
Summary: Python library for reading and writing ipuz puzzle files
Home-page: https://github.com/svisser/ipuz
Author: Simeon Visser
Author-email: simeonvisser@gmail.com
License: MIT
Platform: UNKNOWN
Classifier: Development Status :: 4 - Beta
Classifier: Intended Audience :: Developers
Classifier: License :: OSI Approved :: MIT License
Classifier: Operating System :: OS Independent
Classifier: Programming Language :: Python
Classifier: Programming Language :: Python :: 3.6
Classifier: Programming Language :: Python :: 3.7
Classifier: Programming Language :: Python :: 3.8
Classifier: Programming Language :: Python :: 3.9
Classifier: Topic :: Games/Entertainment :: Puzzle Games
